<?xml version='1.0' encoding='UTF-8'?><record xmlns="http://www.openarchives.org/OAI/2.0/">
  <header>
    <identifier>oai:easy.dans.knaw.nl:easy-dataset:39343</identifier>
    <datestamp>2021-04-15T21:05:01Z</datestamp>
    <setSpec>D60000:D61000</setSpec>
    <setSpec>easy-collection:7</setSpec>
  </header>
  <metadata>
<ddi:codeBook xmlns:ddi="ddi:codebook:2_5" xmlns:xsi="http://www.w3.org/2001/XMLSchema-instance" xmlns:oai_dc="http://www.openarchives.org/OAI/2.0/oai_dc/" xmlns:dc="http://purl.org/dc/elements/1.1/" xsi:schemaLocation="ddi:codebook:2_5 http://www.ddialliance.org/Specification/DDI-Codebook/2.5/XMLSchema/codebook.xsd" version="2.5" xml:lang="en">
   <ddi:docDscr>
      <ddi:citation>
         <ddi:titlStmt>
            <ddi:titl/>
         </ddi:titlStmt>
         <ddi:prodStmt>
            <ddi:producer xml:lang="en">DANS-KNAW</ddi:producer>
         </ddi:prodStmt>
         <ddi:holdings xml:lang="en" URI="http://easy.dans.knaw.nl"/>
      </ddi:citation>
   </ddi:docDscr>
   <ddi:stdyDscr>
      <ddi:citation>
         <ddi:titlStmt>
            <ddi:titl xml:lang="en">Familie-enquête Nederlandse bevolking 2003</ddi:titl>
            <ddi:parTitl xml:lang="en">Family Survey Dutch Population 2003</ddi:parTitl>
            <ddi:IDNo agency="DANS-KNAW">oai:easy.dans.knaw.nl:easy-dataset:39343</ddi:IDNo>
            <ddi:IDNo agency="DOI">https://doi.org/10.17026/dans-xm2-5fue</ddi:IDNo>
         </ddi:titlStmt>
         <ddi:rspStmt>
            <ddi:AuthEnty xml:lang="en" affiliation="Radboud Universiteit Nijmegen">Graaf, N.D. de DAI=info:eu-repo/dai/nl/073779229</ddi:AuthEnty>
            <ddi:AuthEnty xml:lang="en" affiliation="Radboud Universiteit Nijmegen">Graaf, P.M. de DAI=info:eu-repo/dai/nl/073063045</ddi:AuthEnty>
            <ddi:AuthEnty xml:lang="en" affiliation="Radboud Universiteit Nijmegen">Kraaykamp, G. DAI=info:eu-repo/dai/nl/102045836</ddi:AuthEnty>
            <ddi:AuthEnty xml:lang="en" affiliation="Radboud Universiteit Nijmegen">Ultee, W.C. DAI=info:eu-repo/dai/nl/068207166</ddi:AuthEnty>
            <ddi:AuthEnty xml:lang="en">Wouter van Gils</ddi:AuthEnty>
            <ddi:AuthEnty xml:lang="en">Ayce Güveli</ddi:AuthEnty>
            <ddi:AuthEnty xml:lang="en">Eva Jaspers</ddi:AuthEnty>
            <ddi:AuthEnty xml:lang="en">Marcel Lubbers</ddi:AuthEnty>
            <ddi:AuthEnty xml:lang="en">Ruud van der Meulen</ddi:AuthEnty>
            <ddi:AuthEnty xml:lang="en">Arian Need</ddi:AuthEnty>
            <ddi:AuthEnty xml:lang="en">Stijn Ruiter</ddi:AuthEnty>
            <ddi:AuthEnty xml:lang="en">Ellen Verbakel</ddi:AuthEnty>
            <ddi:AuthEnty xml:lang="en">Funding Agency: NWO - Nederlandse Organisatie voor Wetenschappelijk Onderzoek</ddi:AuthEnty>
         </ddi:rspStmt>
         <ddi:distStmt/>
      </ddi:citation>
      <ddi:stdyInfo>
         <ddi:subject>
            <ddi:keyword xml:lang="en">family of origin</ddi:keyword>
            <ddi:keyword xml:lang="en">educational career</ddi:keyword>
            <ddi:keyword xml:lang="en">labor market career</ddi:keyword>
            <ddi:keyword xml:lang="en">family formation</ddi:keyword>
            <ddi:keyword xml:lang="en">income</ddi:keyword>
            <ddi:keyword xml:lang="en">religion</ddi:keyword>
            <ddi:keyword xml:lang="en">leisure time behavior</ddi:keyword>
            <ddi:keyword xml:lang="en">values</ddi:keyword>
            <ddi:keyword xml:lang="en">cultural and material consumption</ddi:keyword>
            <ddi:keyword xml:lang="en">health</ddi:keyword>
            <ddi:keyword xml:lang="en">parental socialization</ddi:keyword>
            <ddi:keyword xml:lang="en">family of origin</ddi:keyword>
            <ddi:keyword xml:lang="en">social participation</ddi:keyword>
            <ddi:keyword xml:lang="en">prosocial behavior</ddi:keyword>
            <ddi:keyword xml:lang="en">media preferences</ddi:keyword>
            <ddi:topcClas xml:lang="en" vocab="NARCIS-classification" vocabURI="http://www.narcis.nl/classification">Social sciences</ddi:topcClas>
            <ddi:topcClas xml:lang="en" vocab="NARCIS-classification" vocabURI="http://www.narcis.nl/classification">Sociology</ddi:topcClas>
         </ddi:subject>
         <ddi:abstract xml:lang="en">Life course and life situation of the Dutch population. Family of origin, educational career, labor market career, family formation, residential career, income, religion, values, leisure time behavior, cultural and material consumption, life satisfaction, health.                          
Longitudinal survey.                          
  
Also available in EASY: Familie-enquête Nederlandse bevolking / Family Survey Dutch Population 1992-1993, 1998, 2000 and 2009</ddi:abstract>
         <ddi:sumDscr>
            <ddi:collDate event="single">2003</ddi:collDate>
         </ddi:sumDscr>
      </ddi:stdyInfo>
      <ddi:dataAccs>
         <ddi:useStmt>
            <ddi:restrctn xml:lang="en">REQUEST_PERMISSION</ddi:restrctn>
            <ddi:conditions xml:lang="en">License: https://dans.knaw.nl/en/about/organisation-and-policy/legal-information/DANSLicence.pdf</ddi:conditions>
         </ddi:useStmt>
      </ddi:dataAccs>
   </ddi:stdyDscr>
   <ddi:fileDscr>
      <ddi:fileTxt xml:lang="nl"/>
   </ddi:fileDscr>
   <ddi:fileDscr>
      <ddi:fileTxt xml:lang="en"/>
   </ddi:fileDscr>
   <ddi:fileDscr>
      <ddi:fileTxt xml:lang="Dutch"/>
   </ddi:fileDscr>
   <ddi:fileDscr>
      <ddi:fileTxt xml:lang="English"/>
   </ddi:fileDscr>
</ddi:codeBook>
  </metadata>
</record>