<?xml version='1.0' encoding='UTF-8'?><record xmlns="http://www.openarchives.org/OAI/2.0/">
  <header>
    <identifier>oai:easy.dans.knaw.nl:easy-dataset:33193</identifier>
    <datestamp>2021-04-15T21:06:26Z</datestamp>
    <setSpec>D40000:D42000</setSpec>
    <setSpec>easy-collection:7</setSpec>
  </header>
  <metadata>
<ddi:codeBook xmlns:ddi="ddi:codebook:2_5" xmlns:xsi="http://www.w3.org/2001/XMLSchema-instance" xmlns:oai_dc="http://www.openarchives.org/OAI/2.0/oai_dc/" xmlns:dc="http://purl.org/dc/elements/1.1/" xsi:schemaLocation="ddi:codebook:2_5 http://www.ddialliance.org/Specification/DDI-Codebook/2.5/XMLSchema/codebook.xsd" version="2.5" xml:lang="en">
   <ddi:docDscr>
      <ddi:citation>
         <ddi:titlStmt>
            <ddi:titl/>
         </ddi:titlStmt>
         <ddi:prodStmt>
            <ddi:producer xml:lang="en">DANS-KNAW</ddi:producer>
         </ddi:prodStmt>
         <ddi:holdings xml:lang="en" URI="http://easy.dans.knaw.nl"/>
      </ddi:citation>
   </ddi:docDscr>
   <ddi:stdyDscr>
      <ddi:citation>
         <ddi:titlStmt>
            <ddi:titl xml:lang="en">Political action II 1981 : Nederland, West-Duitsland, Verenigde Staten; 2e golf </ddi:titl>
            <ddi:parTitl xml:lang="en">Political action II 1981</ddi:parTitl>
            <ddi:IDNo agency="DANS-KNAW">oai:easy.dans.knaw.nl:easy-dataset:33193</ddi:IDNo>
            <ddi:IDNo agency="DOI">https://doi.org/10.17026/dans-xf6-fgj8</ddi:IDNo>
         </ddi:titlStmt>
         <ddi:rspStmt>
            <ddi:AuthEnty xml:lang="en">Allerbeck, K.R., Kaase, M., University of Mannheim * Mannheim, Germany, Klingemann, H.D., Freie Universitaet Berlin * Berlin, Germany, Heunks, F.J., Stouthard, P.C., Katholieke Universiteit Brabant * Tilburg, Thomassen, J.J.A., Deth, J.W. van, Universiteit Twente * Enschede, Barnes, S.H., Farah, B., Inglehart, R., Jennings, K., University of Michigan * Ann Arbor, MI., USA (primary investigator)</ddi:AuthEnty>
            <ddi:AuthEnty xml:lang="en">Getas, Gesellschaft fuer angewandte Sozialpsychologie * Bremen
Survey Research Center, ISR, Univ. of Michigan * Ann Arbor, USA
Instituut voor sociaal-wetenschappelijk onderzoek, IVA * Tilburg (data collector) </ddi:AuthEnty>
         </ddi:rspStmt>
         <ddi:distStmt>
            <ddi:distDate xml:lang="en" date="1990-01-01"/>
            <ddi:distDate xml:lang="en" date="2007-07-09"/>
         </ddi:distStmt>
      </ddi:citation>
      <ddi:stdyInfo>
         <ddi:subject>
            <ddi:keyword xml:lang="en">political science</ddi:keyword>
            <ddi:keyword xml:lang="en">politics, internal</ddi:keyword>
            <ddi:keyword xml:lang="en">participation</ddi:keyword>
            <ddi:topcClas xml:lang="en" vocab="NARCIS-classification" vocabURI="http://www.narcis.nl/classification">Political and administrative sciences</ddi:topcClas>
         </ddi:subject>
         <ddi:abstract xml:lang="en">Cross-national study of conventional and unconventional forms of political participation. Personal satisfaction and deprivation / life problems and how to cope with them / political interest / perception of privileged and underprivileged groups / policy satisfaction for specific issues: terrorism, nuclear power, income differences, agencies, energy problem, role of government, position of women, abortion, employment, pollution / basic view of society / civic competence on local and national level / left, right self placement / meaning of left and right / ranking of important political goals / ( post- )materialist value orientation / performance of present government / good and bad aspects of political parties / sympathy for different social groups/ legitimacy of the political system / approval of protest behaviour / participation in protest behaviour / approval of repressive government action / political efficacy and system responsiveness / attitude towards young people / political trust. Background variables: basic characteristics/ residence/ housing situation/ household characteristics/ characteristics of parental family/household/ occupation/employment/ income/capital assets/ education/ social class/ politics/ religion/ organizational membership</ddi:abstract>
         <ddi:sumDscr>
            <ddi:collDate event="single">1981</ddi:collDate>
         </ddi:sumDscr>
      </ddi:stdyInfo>
      <ddi:dataAccs>
         <ddi:useStmt>
            <ddi:restrctn xml:lang="en">REQUEST_PERMISSION</ddi:restrctn>
            <ddi:conditions xml:lang="en">License: https://dans.knaw.nl/en/about/organisation-and-policy/legal-information/DANSLicence.pdf</ddi:conditions>
         </ddi:useStmt>
      </ddi:dataAccs>
   </ddi:stdyDscr>
</ddi:codeBook>
  </metadata>
</record>