<?xml version='1.0' encoding='UTF-8'?><record xmlns="http://www.openarchives.org/OAI/2.0/">
  <header>
    <identifier>oai:easy.dans.knaw.nl:easy-dataset:162944</identifier>
    <datestamp>2021-04-15T21:08:09Z</datestamp>
    <setSpec>D50000:D51000</setSpec>
    <setSpec>easy-collection:7</setSpec>
  </header>
  <metadata>
<ddi:codeBook xmlns:ddi="ddi:codebook:2_5" xmlns:xsi="http://www.w3.org/2001/XMLSchema-instance" xmlns:oai_dc="http://www.openarchives.org/OAI/2.0/oai_dc/" xmlns:dc="http://purl.org/dc/elements/1.1/" xsi:schemaLocation="ddi:codebook:2_5 http://www.ddialliance.org/Specification/DDI-Codebook/2.5/XMLSchema/codebook.xsd" version="2.5" xml:lang="en">
   <ddi:docDscr>
      <ddi:citation>
         <ddi:titlStmt>
            <ddi:titl/>
         </ddi:titlStmt>
         <ddi:prodStmt>
            <ddi:producer xml:lang="en">DANS-KNAW</ddi:producer>
         </ddi:prodStmt>
         <ddi:holdings xml:lang="en" URI="http://easy.dans.knaw.nl"/>
      </ddi:citation>
   </ddi:docDscr>
   <ddi:stdyDscr>
      <ddi:citation>
         <ddi:titlStmt>
            <ddi:titl xml:lang="eng">A corporate purpose as an antecedent to employee motivation and work engagement</ddi:titl>
            <ddi:IDNo agency="DOI">https://doi.org/10.17026/dans-zze-xsj2</ddi:IDNo>
            <ddi:IDNo agency="DANS-KNAW">oai:easy.dans.knaw.nl:easy-dataset:162944</ddi:IDNo>
         </ddi:titlStmt>
         <ddi:rspStmt>
            <ddi:AuthEnty xml:lang="en" affiliation="Utrecht University">van Tuin, MSc L. ORCID=0000-0001-6481-2487</ddi:AuthEnty>
            <ddi:othId xml:lang="en" role="RightsHolder" affiliation="Utrecht University">van Tuin, MSc L. ORCID=0000-0001-6481-2487, RightsHolder</ddi:othId>
         </ddi:rspStmt>
         <ddi:distStmt>
            <ddi:distDate xml:lang="en" date="19-11-2019"/>
            <ddi:distDate xml:lang="en" date="2016-05-05"/>
            <ddi:distDate xml:lang="en" date="2020-05-05"/>
         </ddi:distStmt>
      </ddi:citation>
      <ddi:stdyInfo>
         <ddi:subject>
            <ddi:keyword xml:lang="eng">Corporate purpose; autonomous motivation; employee engagement; self-determination theory</ddi:keyword>
            <ddi:topcClas xml:lang="en" vocab="NARCIS-classification" vocabURI="http://www.narcis.nl/classification">Psychology</ddi:topcClas>
         </ddi:subject>
         <ddi:abstract xml:lang="eng">It is generally assumed that a corporate purpose aiming to benefit all stakeholders has a positive effect on employee motivation and engagement, but no empirical studies into these specific effects were found. To examine this assumption, a corporate mission and vision matching the definition of a higher purpose were tested in two subsequent studies. The first study (N = 270) was a cross-sectional self-report study. The second study included a longitudinal design (N = 56) modeling purpose, motivation, and engagement in a cross-lagged panel design over three time-points. The results associated purpose with motivation and engagement. The subsequent longitudinal analysis confirmed the presumed directionality from purpose to engagement, but not to motivation. Hence, while a corporate purpose can be added to the list of antecedents to work engagement, the relationship with motivation, despite the significant association with purpose in the cross-sectional study, remains more complicated. The present study adds to the knowledge of the beneficial effects of a broader purpose and responds to the current surge of interest in purpose as an instrument for sustainable business.</ddi:abstract>
         <ddi:sumDscr/>
      </ddi:stdyInfo>
      <ddi:dataAccs>
         <ddi:useStmt>
            <ddi:restrctn xml:lang="en">REQUEST_PERMISSION</ddi:restrctn>
            <ddi:conditions xml:lang="en">License: https://dans.knaw.nl/en/about/organisation-and-policy/legal-information/DANSLicence.pdf</ddi:conditions>
         </ddi:useStmt>
      </ddi:dataAccs>
   </ddi:stdyDscr>
   <ddi:fileDscr>
      <ddi:fileTxt xml:lang="en"/>
   </ddi:fileDscr>
</ddi:codeBook>
  </metadata>
</record>