<?xml version='1.0' encoding='UTF-8'?><record xmlns="http://www.openarchives.org/OAI/2.0/">
  <header>
    <identifier>oai:easy.dans.knaw.nl:easy-dataset:67441</identifier>
    <datestamp>2021-04-15T21:07:36Z</datestamp>
    <setSpec>driver</setSpec>
    <setSpec>D30000:D34000</setSpec>
    <setSpec>easy-collection:7</setSpec>
  </header>
  <metadata>
<ddi:codeBook xmlns:ddi="ddi:codebook:2_5" xmlns:xsi="http://www.w3.org/2001/XMLSchema-instance" xmlns:oai_dc="http://www.openarchives.org/OAI/2.0/oai_dc/" xmlns:dc="http://purl.org/dc/elements/1.1/" xsi:schemaLocation="ddi:codebook:2_5 http://www.ddialliance.org/Specification/DDI-Codebook/2.5/XMLSchema/codebook.xsd" version="2.5" xml:lang="en">
   <ddi:docDscr>
      <ddi:citation>
         <ddi:titlStmt>
            <ddi:titl/>
         </ddi:titlStmt>
         <ddi:prodStmt>
            <ddi:producer xml:lang="en">DANS-KNAW</ddi:producer>
         </ddi:prodStmt>
         <ddi:holdings xml:lang="en" URI="http://easy.dans.knaw.nl"/>
      </ddi:citation>
   </ddi:docDscr>
   <ddi:stdyDscr>
      <ddi:citation>
         <ddi:titlStmt>
            <ddi:titl xml:lang="en">Historisch Leiden in Kaart: Stadsuitbreiding, 1611</ddi:titl>
            <ddi:IDNo agency="DOI">https://doi.org/10.17026/dans-zgk-y8gg</ddi:IDNo>
            <ddi:IDNo agency="DANS-KNAW">oai:easy.dans.knaw.nl:easy-dataset:67441</ddi:IDNo>
         </ddi:titlStmt>
         <ddi:rspStmt>
            <ddi:AuthEnty xml:lang="en" affiliation="Leiden University">Oosten, Dr R.M.R. van DAI=info:eu-repo/dai/nl/300298986</ddi:AuthEnty>
            <ddi:othId xml:lang="en" role="">Funding Agency: Data Archiving and Networked Services - DANS, subsidie Klein data Project - KDP 2016</ddi:othId>
         </ddi:rspStmt>
         <ddi:distStmt/>
      </ddi:citation>
      <ddi:stdyInfo>
         <ddi:subject>
            <ddi:keyword xml:lang="en">kavels</ddi:keyword>
            <ddi:keyword xml:lang="en">stadsuitbreiding Leiden, 1611</ddi:keyword>
            <ddi:topcClas xml:lang="en" vocab="NARCIS-classification" vocabURI="http://www.narcis.nl/classification">History</ddi:topcClas>
         </ddi:subject>
         <ddi:abstract xml:lang="en">Verkoop van de kavels van de stadsuitbreiding van Leiden in 1611.</ddi:abstract>
         <ddi:sumDscr>
            <ddi:collDate event="single">1611</ddi:collDate>
         </ddi:sumDscr>
      </ddi:stdyInfo>
      <ddi:dataAccs>
         <ddi:useStmt>
            <ddi:conditions xml:lang="en">License: http://creativecommons.org/publicdomain/zero/1.0</ddi:conditions>
         </ddi:useStmt>
      </ddi:dataAccs>
   </ddi:stdyDscr>
   <ddi:fileDscr>
      <ddi:fileTxt xml:lang="nl"/>
   </ddi:fileDscr>
</ddi:codeBook>
  </metadata>
</record>