<?xml version='1.0' encoding='UTF-8'?><record xmlns="http://www.openarchives.org/OAI/2.0/">
  <header>
    <identifier>oai:easy.dans.knaw.nl:easy-dataset:32458</identifier>
    <datestamp>2021-04-15T21:05:49Z</datestamp>
    <setSpec>D50000:D51000</setSpec>
    <setSpec>driver</setSpec>
    <setSpec>easy-collection:7</setSpec>
  </header>
  <metadata>
<ddi:codeBook xmlns:ddi="ddi:codebook:2_5" xmlns:xsi="http://www.w3.org/2001/XMLSchema-instance" xmlns:oai_dc="http://www.openarchives.org/OAI/2.0/oai_dc/" xmlns:dc="http://purl.org/dc/elements/1.1/" xsi:schemaLocation="ddi:codebook:2_5 http://www.ddialliance.org/Specification/DDI-Codebook/2.5/XMLSchema/codebook.xsd" version="2.5" xml:lang="en">
   <ddi:docDscr>
      <ddi:citation>
         <ddi:titlStmt>
            <ddi:titl/>
         </ddi:titlStmt>
         <ddi:prodStmt>
            <ddi:producer xml:lang="en">DANS-KNAW</ddi:producer>
         </ddi:prodStmt>
         <ddi:holdings xml:lang="en" URI="http://easy.dans.knaw.nl"/>
      </ddi:citation>
   </ddi:docDscr>
   <ddi:stdyDscr>
      <ddi:citation>
         <ddi:titlStmt>
            <ddi:titl xml:lang="en">Echtscheiding, ouderschap en zelfwaardering 1991-1994</ddi:titl>
            <ddi:parTitl xml:lang="en">Divorce, parenthood and self-esteem 1991-1994</ddi:parTitl>
            <ddi:IDNo agency="DANS-KNAW">oai:easy.dans.knaw.nl:easy-dataset:32458</ddi:IDNo>
            <ddi:IDNo agency="DOI">https://doi.org/10.17026/dans-zc3-cb9y</ddi:IDNo>
         </ddi:titlStmt>
         <ddi:rspStmt>
            <ddi:AuthEnty xml:lang="en">Schooten, J.H.C. van, Velserbroek (primary investigator)</ddi:AuthEnty>
            <ddi:AuthEnty xml:lang="en">J.H.C. van Schooten, Westbroekerweg 28 (depositor)</ddi:AuthEnty>
         </ddi:rspStmt>
         <ddi:distStmt>
            <ddi:distDate xml:lang="en" date="1994-01-01"/>
            <ddi:distDate xml:lang="en" date="2007-07-23"/>
         </ddi:distStmt>
      </ddi:citation>
      <ddi:stdyInfo>
         <ddi:subject>
            <ddi:keyword xml:lang="en">psychology</ddi:keyword>
            <ddi:keyword xml:lang="en">children</ddi:keyword>
            <ddi:keyword xml:lang="en">family life</ddi:keyword>
            <ddi:keyword xml:lang="en">interpersonal relations</ddi:keyword>
            <ddi:keyword xml:lang="en">divorce</ddi:keyword>
            <ddi:keyword xml:lang="en">parental role</ddi:keyword>
            <ddi:keyword xml:lang="en">self-esteem</ddi:keyword>
            <ddi:topcClas xml:lang="en" vocab="NARCIS-classification" vocabURI="http://www.narcis.nl/classification">Psychology</ddi:topcClas>
         </ddi:subject>
         <ddi:abstract xml:lang="en">A qualitative study for theory development. A theory was developed which elucidates how divorced parents arrange their parenthood, before and after the end phase of definitively breaking apart. Interviews with detailed questions about interaction with and attitude towards former partner, based on Symbolic Interactionism and The Discovery of Grounded Theory and combined with findings from theories which relate to stress and coping. Items: building a relation, family / rejection as partner / exclusion as partner / avoid partner / adjustment to partner / take distance from partner / compromising / dialogue / resistance against partner / social support / break the contract / break up partnership / Child Welfare Council - child protection / guardianship / ordinance by magistrate of juvenile court / duration of marriage / year of divorce / arrangements concerning parental access / existence of new relationship. Background variables: basic characteristics/ household characteristics/ occupation/employment/ education</ddi:abstract>
         <ddi:sumDscr>
            <ddi:collDate event="single">1991 * 1994</ddi:collDate>
         </ddi:sumDscr>
      </ddi:stdyInfo>
      <ddi:dataAccs>
         <ddi:useStmt>
            <ddi:restrctn xml:lang="en">OPEN_ACCESS_FOR_REGISTERED_USERS</ddi:restrctn>
            <ddi:conditions xml:lang="en">License: https://dans.knaw.nl/en/about/organisation-and-policy/legal-information/DANSLicence.pdf</ddi:conditions>
         </ddi:useStmt>
      </ddi:dataAccs>
   </ddi:stdyDscr>
</ddi:codeBook>
  </metadata>
</record>