<?xml version='1.0' encoding='UTF-8'?><record xmlns="http://www.openarchives.org/OAI/2.0/">
  <header>
    <identifier>oai:easy.dans.knaw.nl:easy-dataset:163275</identifier>
    <datestamp>2021-04-15T21:08:10Z</datestamp>
    <setSpec>D60000:D65000</setSpec>
    <setSpec>easy-collection:7</setSpec>
  </header>
  <metadata>
<ddi:codeBook xmlns:ddi="ddi:codebook:2_5" xmlns:xsi="http://www.w3.org/2001/XMLSchema-instance" xmlns:oai_dc="http://www.openarchives.org/OAI/2.0/oai_dc/" xmlns:dc="http://purl.org/dc/elements/1.1/" xsi:schemaLocation="ddi:codebook:2_5 http://www.ddialliance.org/Specification/DDI-Codebook/2.5/XMLSchema/codebook.xsd" version="2.5" xml:lang="en">
   <ddi:docDscr>
      <ddi:citation>
         <ddi:titlStmt>
            <ddi:titl/>
         </ddi:titlStmt>
         <ddi:prodStmt>
            <ddi:producer xml:lang="en">DANS-KNAW</ddi:producer>
         </ddi:prodStmt>
         <ddi:holdings xml:lang="en" URI="http://easy.dans.knaw.nl"/>
      </ddi:citation>
   </ddi:docDscr>
   <ddi:stdyDscr>
      <ddi:citation>
         <ddi:titlStmt>
            <ddi:titl xml:lang="eng">Predictive land value modelling in Guatemala City using a geo-statistical approach and Space Syntax</ddi:titl>
            <ddi:IDNo agency="DOI">https://doi.org/10.17026/dans-23t-7a8u</ddi:IDNo>
            <ddi:IDNo agency="DANS-KNAW">oai:easy.dans.knaw.nl:easy-dataset:163275</ddi:IDNo>
         </ddi:titlStmt>
         <ddi:rspStmt>
            <ddi:AuthEnty xml:lang="en" affiliation="Faculty of Geo-information Science and Earth Observation (ITC), University of Twente">Morales, MSc ANDRES ORCID=0000-0001-8494-1163</ddi:AuthEnty>
            <ddi:othId xml:lang="en" role="RightsHolder" affiliation="Jose Andres Morales">Morales, MSc JA ORCID=0000-0001-8494-1163, RightsHolder</ddi:othId>
         </ddi:rspStmt>
         <ddi:distStmt>
            <ddi:distDate xml:lang="en" date="2020-05-29"/>
            <ddi:distDate xml:lang="en" date="2020-06-05"/>
         </ddi:distStmt>
      </ddi:citation>
      <ddi:stdyInfo>
         <ddi:subject>
            <ddi:keyword xml:lang="eng">land value; Guatemala City; Space Syntax; regression-kriging; geostatistics;</ddi:keyword>
            <ddi:topcClas xml:lang="en" vocab="NARCIS-classification" vocabURI="http://www.narcis.nl/classification">Urban and rural planning</ddi:topcClas>
         </ddi:subject>
         <ddi:abstract xml:lang="eng">The datasets were produced during the doctoral research titled "A modelling framework to estimate the effects of future transport interventions on land values". Specifically, the datasets were produced and prepared with the purpose of training a geostatistical model and construct a residential land value map for Guatemala City using a predictive approach. The file "gc_log" contains a set of spatial points representing parcel centroids of the observations that were used to train a regression-kriging model. A spatialized variable selection was implemented in order to retain only important variables. The "grid_prediction.csv" contains a set of spatial points representing the centroids of an hexagonal tessellation containing values for all the required predictors of land value. The "research_code.R" file contains the scripts developed to implement the spatial variable selection, train the regression-kriging model and construct the land value map.</ddi:abstract>
         <ddi:sumDscr>
            <ddi:collDate event="single">2008-2014</ddi:collDate>
         </ddi:sumDscr>
      </ddi:stdyInfo>
      <ddi:dataAccs>
         <ddi:useStmt>
            <ddi:restrctn xml:lang="en">REQUEST_PERMISSION</ddi:restrctn>
            <ddi:conditions xml:lang="en">License: https://dans.knaw.nl/en/about/organisation-and-policy/legal-information/DANSLicence.pdf</ddi:conditions>
         </ddi:useStmt>
      </ddi:dataAccs>
   </ddi:stdyDscr>
   <ddi:fileDscr>
      <ddi:fileTxt xml:lang="en"/>
   </ddi:fileDscr>
</ddi:codeBook>
  </metadata>
</record>