<?xml version='1.0' encoding='UTF-8'?><record xmlns="http://www.openarchives.org/OAI/2.0/">
  <header>
    <identifier>oai:easy.dans.knaw.nl:easy-dataset:32473</identifier>
    <datestamp>2021-04-15T21:05:49Z</datestamp>
    <setSpec>D60000:D68000</setSpec>
    <setSpec>easy-collection:7</setSpec>
  </header>
  <metadata>
<ddi:codeBook xmlns:ddi="ddi:codebook:2_5" xmlns:xsi="http://www.w3.org/2001/XMLSchema-instance" xmlns:oai_dc="http://www.openarchives.org/OAI/2.0/oai_dc/" xmlns:dc="http://purl.org/dc/elements/1.1/" xsi:schemaLocation="ddi:codebook:2_5 http://www.ddialliance.org/Specification/DDI-Codebook/2.5/XMLSchema/codebook.xsd" version="2.5" xml:lang="en">
   <ddi:docDscr>
      <ddi:citation>
         <ddi:titlStmt>
            <ddi:titl/>
         </ddi:titlStmt>
         <ddi:prodStmt>
            <ddi:producer xml:lang="en">DANS-KNAW</ddi:producer>
         </ddi:prodStmt>
         <ddi:holdings xml:lang="en" URI="http://easy.dans.knaw.nl"/>
      </ddi:citation>
   </ddi:docDscr>
   <ddi:stdyDscr>
      <ddi:citation>
         <ddi:titlStmt>
            <ddi:titl xml:lang="en">Niet-gebruik van de Toeslagenwet 1991</ddi:titl>
            <ddi:parTitl xml:lang="en">Non-use of the supplementary benefits law ( 'Toeslagenwet' ) 1991</ddi:parTitl>
            <ddi:IDNo agency="DANS-KNAW">oai:easy.dans.knaw.nl:easy-dataset:32473</ddi:IDNo>
            <ddi:IDNo agency="DOI">https://doi.org/10.17026/dans-zrf-4m9p</ddi:IDNo>
         </ddi:titlStmt>
         <ddi:rspStmt>
            <ddi:AuthEnty xml:lang="en">Meiners, D., Sociale verzekeringsraad, SVR * Zoetermeer (primary investigator)</ddi:AuthEnty>
            <ddi:AuthEnty xml:lang="en">Sociale Verzekeringsraad (depositor)</ddi:AuthEnty>
            <ddi:AuthEnty xml:lang="en">Sociale VerzekeringsRaad, SVR * Zoetermeer (research initiator) </ddi:AuthEnty>
            <ddi:AuthEnty xml:lang="en">Nederlands instituut voor de publieke opinie en het marktonderzoek, NIPO * Amsterdam (data collector) </ddi:AuthEnty>
         </ddi:rspStmt>
         <ddi:distStmt>
            <ddi:distDate xml:lang="en" date="1993-01-01"/>
            <ddi:distDate xml:lang="en" date="2007-07-20"/>
         </ddi:distStmt>
      </ddi:citation>
      <ddi:stdyInfo>
         <ddi:subject>
            <ddi:keyword xml:lang="en">sociology</ddi:keyword>
            <ddi:keyword xml:lang="en">economy</ddi:keyword>
            <ddi:keyword xml:lang="en">finance</ddi:keyword>
            <ddi:keyword xml:lang="en">welfare</ddi:keyword>
            <ddi:topcClas xml:lang="en" vocab="NARCIS-classification" vocabURI="http://www.narcis.nl/classification">Social security studies</ddi:topcClas>
         </ddi:subject>
         <ddi:abstract xml:lang="en">Non-use of additional social benefits law. People who receive social security benefits, whose income is below a 'social minimum' can appeal to the law on additional social benefits. Not all of them use this opportunity. Research on character and cause of non-use. After becoming unemployed being informed about possible social benefits? / Way of being informed / judgement about being informed on possible social benefits / R. receiving additional social benefits / R. declared unfit for work: percentage? / Kind of social benefit received by respondent: unemployment ( WW ) / unfit ( WAO ) / widowed ( AWW ) / Knowledge about mechanism of additional social benefits law / understanding the mechanism of the law / R. experienced problems with additional social benefits law/ causes of the problems / clearing the problems / talking to others about the additional social benefits law / 'the 1990-rule' / heard about rule for self-support = 1990-generation / R. was ever refused an application for additional support / Result of possible appeal against refusing additional support / R. has relatives or friends with receiving social benefits / talking to others about receiving social benefits. / R.'s source of income / frequency of receiving 'income' / net income of respondent / estimate of salary by the hour, day, week month, year / source of income of R.'s partner: salary, AAW, WAO, WW, Sickness, AOW - old age pension, scholarship, child allowance, holiday pay, other social benefits. Ever since being out of work, respondent economized on paying visits to others, clothing, food, club memberships, insurances, housing = moved to smaller house / possibility to make ends meet for respondent / net income needed to make ends meet / statements on civil servants/ tasks of civil servants / statements about filling in forms / social benefits / talking about social benefits / dependency / unemployment. Background variables: basic characteristics/ household characteristics/ education</ddi:abstract>
         <ddi:sumDscr>
            <ddi:collDate event="single">1989</ddi:collDate>
         </ddi:sumDscr>
      </ddi:stdyInfo>
      <ddi:dataAccs>
         <ddi:useStmt>
            <ddi:restrctn xml:lang="en">REQUEST_PERMISSION</ddi:restrctn>
            <ddi:conditions xml:lang="en">License: https://dans.knaw.nl/en/about/organisation-and-policy/legal-information/DANSLicence.pdf</ddi:conditions>
         </ddi:useStmt>
      </ddi:dataAccs>
   </ddi:stdyDscr>
</ddi:codeBook>
  </metadata>
</record>